__init__.py
api/__init__.py
api/atera.py
diffuse/__init__.py
gpt/__init__.py
harvest/__init__.py
utils/__init__.py
cobragpt-0.0.1.dist-info/LICENSE
cobragpt-0.0.1.dist-info/METADATA
cobragpt-0.0.1.dist-info/WHEEL
cobragpt-0.0.1.dist-info/top_level.txt
cobragpt-0.0.1.dist-info/RECORD
