Metadata-Version: 2.1
Name: cobragpt
Version: 0.0.1
Summary: An interface for interacting with various generative AI models.
Author-email: song-dog <coyote@coyote-ltd.com>
License: MIT License
Project-URL: Homepage, https://github.com/song-dog/cobragpt
Project-URL: Bug Tracker, https://github.com/song-dog/cobragpt/issues
Classifier: Programming Language :: Python :: 3
Classifier: License :: OSI Approved :: MIT License
Classifier: Operating System :: OS Independent
Requires-Python: >=3.9
License-File: LICENSE
